bxsolana/__init__.py
bxsolana/examples/__init__.py
bxsolana/examples/constants.py
bxsolana/examples/order_lifecycle.py
bxsolana/examples/order_utils.py
bxsolana/examples/request_utils.py
bxsolana/examples/stream_utils.py
bxsolana/examples/transaction_request_utils.py
bxsolana/provider/__init__.py
bxsolana/provider/base.py
bxsolana/provider/constants.py
bxsolana/provider/grpc.py
bxsolana/provider/http.py
bxsolana/provider/http_error.py
bxsolana/provider/jsonrpc_patch.py
bxsolana/provider/package_info.py
bxsolana/provider/ws.py
bxsolana/transaction/__init__.py
bxsolana/transaction/memo.py
bxsolana/transaction/private_txs.py
bxsolana/transaction/signing.py
bxsolana/utils/__init__.py
bxsolana/utils/timestamp.py
bxsolana_trader-2.2.9.dist-info/licenses/LICENSE
test/__init__.py
test/unit/__init__.py
test/unit/transaction/__init__.py
test/unit/transaction/test_memo.py
test/unit/transaction/test_signing.py
bxsolana_trader-2.2.9.dist-info/METADATA
bxsolana_trader-2.2.9.dist-info/WHEEL
bxsolana_trader-2.2.9.dist-info/top_level.txt
bxsolana_trader-2.2.9.dist-info/RECORD
