Metadata-Version: 2.4
Name: bxsolana-trader
Version: 2.2.9
Summary: Python SDK for bloXroute's Solana Trader API
Home-page: https://github.com/bloXroute-Labs/solana-trader-client-python
Author: bloXroute Labs
Author-email: support@bloxroute.com
Keywords: openbook,solana,blockchain,trader,grpc,stream,raydium,jupiter
Classifier: Programming Language :: Python :: 3
License-File: LICENSE
Requires-Dist: aiohttp==3.9.0
Requires-Dist: grpclib==0.4.3
Requires-Dist: aiounittest==1.4.1
Requires-Dist: base58==2.1.1
Requires-Dist: solana==0.31.0
Requires-Dist: solders==0.19.0
Requires-Dist: bx-jsonrpc-py==0.2.0
Requires-Dist: bxsolana-trader-proto==0.1.8
Dynamic: license-file
